ipfs_datasets_py/__init__.py
ipfs_datasets_py/config.py
ipfs_datasets_py/ipfs_datasets.py
ipfs_datasets_py/ipfs_knn_index.py
ipfs_datasets_py/ipfs_multiformats.py
ipfs_datasets_py/ipfs_parquet_to_car.py
ipfs_datasets_py/s3_kit.py
ipfs_datasets_py/test_fio.py
ipfs_datasets_py-0.0.10.dist-info/LICENSE
ipfs_datasets_py-0.0.10.dist-info/METADATA
ipfs_datasets_py-0.0.10.dist-info/WHEEL
ipfs_datasets_py-0.0.10.dist-info/top_level.txt
ipfs_datasets_py-0.0.10.dist-info/RECORD
